README.md
setup.py
manage_crystal/__init__.py
manage_crystal/file_parser.py
manage_crystal/file_writer.py
manage_crystal/manage_crystal
manage_crystal/periodic_table.py
manage_crystal/trajec_crystal
manage_crystal/utils.py
manage_crystal.egg-info/PKG-INFO
manage_crystal.egg-info/SOURCES.txt
manage_crystal.egg-info/dependency_links.txt
manage_crystal.egg-info/requires.txt
manage_crystal.egg-info/top_level.txt