Metadata-Version: 2.1
Name: manage-crystal
Version: 0.1.0
Summary: Tools for manipulating crystal formats
Home-page: https://github.com/danieleongari/manage_crystal
Author: Daniele Ongari
Author-email: daniele.ongari@epfl.ch
License: Creative Commons
Platform: UNKNOWN
Classifier: Programming Language :: Python
Provides-Extra: pre-commit
